Metadata-Version: 2.4
Name: r3frame2
Version: 0.0.8
Summary: A neat little thing... with nightly updates
Home-page: https://github.com/r3shape/r3frame2
Author: Izaiyah Stokes
Author-email: d34d0s.dev@gmail.com
Classifier: Programming Language :: Python :: 3.12
Classifier: License :: OSI Approved :: MIT License
Classifier: Operating System :: OS Independent
License-File: LICENSE
Requires-Dist: pygame-ce
Requires-Dist: pytz
Requires-Dist: numpy
Requires-Dist: numba
Dynamic: author
Dynamic: author-email
Dynamic: classifier
Dynamic: description
Dynamic: description-content-type
Dynamic: home-page
Dynamic: license-file
Dynamic: requires-dist
Dynamic: summary
